data_skew/__init__.py
data_skew/data_skew.py
data_skew-0.1.2.dist-info/LICENSE
data_skew-0.1.2.dist-info/METADATA
data_skew-0.1.2.dist-info/WHEEL
data_skew-0.1.2.dist-info/top_level.txt
data_skew-0.1.2.dist-info/RECORD
