Metadata-Version: 2.1
Name: data-skew
Version: 0.1.2
Summary: Create DataFrames based on a required bias
Home-page: http://github.com/JVoogt/data-skew
Author: J Voogt
Author-email: jvoogt1@outlook.com
License: MIT
Platform: UNKNOWN
